gradio/__init__.py
gradio/analytics.py
gradio/blocks.py
gradio/components.py
gradio/context.py
gradio/data_classes.py
gradio/deprecation.py
gradio/events.py
gradio/exceptions.py
gradio/external.py
gradio/external_utils.py
gradio/flagging.py
gradio/helpers.py
gradio/inputs.py
gradio/interface.py
gradio/interpretation.py
gradio/ipython_ext.py
gradio/layouts.py
gradio/mix.py
gradio/networking.py
gradio/outputs.py
gradio/pipelines.py
gradio/processing_utils.py
gradio/queueing.py
gradio/ranged_response.py
gradio/reload.py
gradio/routes.py
gradio/strings.py
gradio/templates.py
gradio/tunneling.py
gradio/utils.py
gradio/version.txt
gradio/templates/frontend/favicon.png
gradio/templates/frontend/index.html
gradio/templates/frontend/assets/BlockLabel-1bfe4e4d.js
gradio/templates/frontend/assets/BlockLabel-1bfe4e4d.js.map
gradio/templates/frontend/assets/BlockTitle-4740606e.js
gradio/templates/frontend/assets/BlockTitle-4740606e.js.map
gradio/templates/frontend/assets/Blocks-85470727.js
gradio/templates/frontend/assets/Blocks-85470727.js.map
gradio/templates/frontend/assets/Blocks-9463a1f9.css
gradio/templates/frontend/assets/Button-76dfdfa3.css
gradio/templates/frontend/assets/Button-f9baf3c9.js
gradio/templates/frontend/assets/Button-f9baf3c9.js.map
gradio/templates/frontend/assets/ColorPicker-76ff4dc7.css
gradio/templates/frontend/assets/ColorPicker.svelte_svelte_type_style_lang-700774cc.js.map
gradio/templates/frontend/assets/Column-2853eb31.css
gradio/templates/frontend/assets/Column-b01b500a.js
gradio/templates/frontend/assets/Column-b01b500a.js.map
gradio/templates/frontend/assets/Column.svelte_svelte_type_style_lang-bf454eb5.js.map
gradio/templates/frontend/assets/Copy-0599f89a.js
gradio/templates/frontend/assets/Copy-0599f89a.js.map
gradio/templates/frontend/assets/Download-f88eef63.js
gradio/templates/frontend/assets/Download-f88eef63.js.map
gradio/templates/frontend/assets/DropdownArrow-5fa4dd09.css
gradio_stable_fork-3.32.6.dist-info/METADATA
gradio_stable_fork-3.32.6.dist-info/WHEEL
gradio_stable_fork-3.32.6.dist-info/entry_points.txt
gradio_stable_fork-3.32.6.dist-info/licenses/LICENSE
gradio_stable_fork-3.32.6.dist-info/RECORD
